{"stats":{"total":5,"retries":5,"passed":4,"failed":1},"status":"failed","newTests":[{"id":"abe3bfb02236e41b61f3ae39be2fd735","name":"Create, update annd delete article with custom title","status":"passed","duration":2795},{"id":"6c37e203301a84f63c03d054f1e926d9","name":"Hibrid API + UI Test (Fast Login)","status":"passed","duration":1171},{"id":"dec5e7c4c32d0738582d71a00309b155","name":"Hybrid Login via Playwright API Request","status":"passed","duration":1053},{"id":"bbb2d5349fbacfa3e925616438aeb5aa","name":"Create article with check Screenshot","status":"passed","duration":8256},{"id":"9296fddcf0dd0ae4055f553f5855294c","name":"Create article with defoult title","status":"passed","duration":6162},{"id":"6e91ed9b45fa103b0f71c054b15ed093","name":"Create article with defoult title","status":"passed","duration":2609},{"id":"cff1e45af6d98427e3f955dcb954939e","name":"Hibrid API + UI Test (Fast Login)","status":"passed","duration":5056},{"id":"7f8d2c2a47b7a38738e73ee8f467a76d","name":"Create, update annd delete article with custom title","status":"passed","duration":7925},{"id":"5424b39254621d1bd51afc21b739518b","name":"Hybrid Login via Playwright API Request","status":"passed","duration":5253},{"id":"8a99dc82c4858e7de2458c360c2cffdb","name":"Create article with check Screenshot","status":"failed","duration":3717}],"flakyTests":[],"retryTests":[],"name":"Allure Report","duration":11345,"createdAt":1772987154184,"plugin":"Awesome","meta":{"reportId":"f37cf877-3ed6-4d99-9794-811bf78d431d","singleFile":false,"withTestResultsLinks":true},"pullRequestHref":"","jobHref":"https://github.com/baleksandr/playwright-conduit-framework/actions/runs/22825027970"}